[
    {
        "id": 1,
        "alt": "Sneaker 1",
        "image": "/assets/image-product-1.jpg",
        "thumbnail": "/assets/image-product-1-thumbnail.jpg"
    },
    {
        "id" : 2,
        "alt": "Sneaker 2",
        "image": "/assets/image-product-2.jpg",
        "thumbnail": "/assets/image-product-2-thumbnail.jpg"
    },
    {
        "id" : 3,
        "alt": "Sneaker 3",
        "image": "/assets/image-product-3.jpg",
        "thumbnail": "/assets/image-product-3-thumbnail.jpg"
    },
    {
        "id" : 4,
        "alt": "Sneaker 4",
        "image": "/assets/image-product-4.jpg",
        "thumbnail": "/assets/image-product-4-thumbnail.jpg"
    }
]